ncloud_vnas/__init__.py
ncloud_vnas/api_client.py
ncloud_vnas/configuration.py
ncloud_vnas/rest.py
ncloud_vnas/api/__init__.py
ncloud_vnas/api/v2_api.py
ncloud_vnas/model/__init__.py
ncloud_vnas/model/add_nas_volume_access_control_request.py
ncloud_vnas/model/add_nas_volume_access_control_response.py
ncloud_vnas/model/change_nas_volume_size_request.py
ncloud_vnas/model/change_nas_volume_size_response.py
ncloud_vnas/model/common_code.py
ncloud_vnas/model/create_nas_volume_instance_request.py
ncloud_vnas/model/create_nas_volume_instance_response.py
ncloud_vnas/model/delete_nas_volume_instances_request.py
ncloud_vnas/model/delete_nas_volume_instances_response.py
ncloud_vnas/model/get_nas_volume_instance_detail_request.py
ncloud_vnas/model/get_nas_volume_instance_detail_response.py
ncloud_vnas/model/get_nas_volume_instance_list_request.py
ncloud_vnas/model/get_nas_volume_instance_list_response.py
ncloud_vnas/model/nas_volume_instance.py
ncloud_vnas/model/remove_nas_volume_access_control_request.py
ncloud_vnas/model/remove_nas_volume_access_control_response.py
ncloud_vnas/model/set_nas_volume_access_control_request.py
ncloud_vnas/model/set_nas_volume_access_control_response.py
test/__init__.py
test/test_v2_api.py
ncloud_vnas-1.0.1.dist-info/LICENSE
ncloud_vnas-1.0.1.dist-info/METADATA
ncloud_vnas-1.0.1.dist-info/WHEEL
ncloud_vnas-1.0.1.dist-info/top_level.txt
ncloud_vnas-1.0.1.dist-info/RECORD
