Metadata-Version: 1.0
Name: ncloud-vnas
Version: 1.0.1
Summary: vnas
Home-page: UNKNOWN
Author: UNKNOWN
Author-email: UNKNOWN
License: UNKNOWN
Keywords: vnas
Platform: UNKNOWN
